prune_norminette/__init__.py
prune_norminette/main.py
prune_norminette/rules/content_python_file/check_basemodel_in_payloads.py
prune_norminette/rules/content_python_file/check_core_model_usage.py
prune_norminette/rules/content_python_file/check_missing_str_method.py
prune_norminette/rules/content_python_file/check_textchoices_in_enums.py
prune_norminette/rules/content_python_file/check_urls_name_parameter.py
prune_norminette/rules/content_python_file/check_view_function_naming.py
prune_norminette/rules/files_emplacement/check_pages_folder_structure.py
prune_norminette/rules/files_emplacement/check_templates_static_structure.py
prune_norminette/rules/formate/normalize_django_tags_spacing.py
prune_norminette/rules/formate/remove_double_empty_lines.py
prune_norminette/rules/project_config/check_environment_class_in_settings.py
prune_norminette/rules/project_config/check_for_envsettings_class_in_settings.py
prune_norminette/rules/project_config/check_gitignore_content.py
prune_norminette/rules/project_config/check_pyproject_configuration.py
prune_norminette/rules/project_config/check_uv_use.py
prune_norminette/rules/project_config/check_valid_whitenoise_and_static_paths.py
prune_norminette/rules/project_config/utils/read_settings.py
prune_norminette/rules/templates/check_component_and_layout_file_placement.py
prune_norminette/rules/templates/check_svg_files_location_and_extension.py
prune_norminette/rules/templates/check_svg_inclusion_paths.py
prune_norminette/utils/display_result.py
prune_norminette/utils/run_checks.py
prune_norminette/utils/setup_django.py
prune_norminette/utils/rules/display_rules.py
prune_norminette/utils/rules/extract_rules.py
prune_norminette/utils/rules/generate_readme.py
prune_norminette-2.0.3.dist-info/METADATA
prune_norminette-2.0.3.dist-info/WHEEL
prune_norminette-2.0.3.dist-info/entry_points.txt
prune_norminette-2.0.3.dist-info/top_level.txt
prune_norminette-2.0.3.dist-info/RECORD
