Metadata-Version: 2.4
Name: prune_norminette
Version: 2.0.3
Summary: A tool to ensure that code adheres to Prune's coding standards.
Author-email: Arnout <bastien@prune.sh>
Project-URL: Made_by, https://prune.sh/
Keywords: norminette,django,code-quality
Classifier: Programming Language :: Python :: 3
Classifier: License :: OSI Approved :: MIT License
Classifier: Operating System :: OS Independent
Requires-Python: <4.0,>=3.12
Requires-Dist: build>=1.3.0
Requires-Dist: twine>=6.1.0
